{"cameraMode":{"drawMode":0,"name":"Shaded","section":"Shading Mode"},"sceneLighting":true,"audioPlay":false,"sceneViewState":{"showFog":true,"showMaterialUpdate":false,"showSkybox":true,"showFlares":true,"showImageEffects":true,"showParticleSystems":true},"in2DMode":false,"pivot":{"x":14.87977409362793,"y":18.284664154052736,"z":-2.3955230712890627},"rotation":{"x":0.253896027803421,"y":0.07039925456047058,"z":-0.01869271881878376,"w":0.9645431637763977},"size":84.0470199584961,"orthographic":false}